obs_cli.py
obs_cli-0.8.3.dist-info/licenses/LICENSE
obs_cli-0.8.3.dist-info/METADATA
obs_cli-0.8.3.dist-info/WHEEL
obs_cli-0.8.3.dist-info/entry_points.txt
obs_cli-0.8.3.dist-info/top_level.txt
obs_cli-0.8.3.dist-info/RECORD
