Metadata-Version: 2.4
Name: obs-cli
Version: 0.8.3
Summary: OBS CLI
Author-email: Philipp Schmitt <philipp@schmitt.co>
License:                     GNU GENERAL PUBLIC LICENSE
Project-URL: Homepage, https://github.com/pschmitt/obs-cli
Project-URL: Documentation, https://github.com/pschmitt/obs-cli/blob/HEAD/README.md
Project-URL: Repository, https://github.com/pschmitt/obs-cli
Project-URL: Issues, https://github.com/pschmitt/obs-cli/issues
Keywords: obs,obs-studio
Classifier: Programming Language :: Python :: 3
Requires-Python: >=3.9
License-File: LICENSE
Requires-Dist: obsws-python
Requires-Dist: rich
Dynamic: license-file
